LICENSE
MANIFEST.in
README.md
VERSION
requirements.cv
requirements.seq
requirements.txt
setup.py
mmif/__init__.py
mmif/res/__init__.py
mmif/res/clams.vocabulary.yaml
mmif/res/do-not-edit.txt
mmif/res/mmif.json
mmif/serialize/__init__.py
mmif/serialize/annotation.py
mmif/serialize/mmif.py
mmif/serialize/model.py
mmif/serialize/view.py
mmif/utils/__init__.py
mmif/utils/sequence_helper.py
mmif/utils/text_document_helper.py
mmif/utils/timeunit_helper.py
mmif/utils/video_document_helper.py
mmif/utils/cli/__init__.py
mmif/utils/cli/rewind.py
mmif/utils/cli/source.py
mmif/ver/__init__.py
mmif/ver/do-not-edit.txt
mmif/vocabulary/__init__.py
mmif/vocabulary/annotation_types.py
mmif/vocabulary/base_types.py
mmif/vocabulary/do-not-edit.txt
mmif/vocabulary/document_types.py
mmif_docloc_http/__init__.py
mmif_python.egg-info/PKG-INFO
mmif_python.egg-info/SOURCES.txt
mmif_python.egg-info/dependency_links.txt
mmif_python.egg-info/entry_points.txt
mmif_python.egg-info/requires.txt
mmif_python.egg-info/top_level.txt
tests/test_serialize.py
tests/test_utils.py
tests/test_utils_cli.py
tests/test_versioncompat.py
tests/test_vocab.py