Metadata-Version: 2.4
Name: mmif-python
Version: 1.1.1
Summary: Python implementation of MultiMedia Interchange Format specification. (https://mmif.clams.ai)
Home-page: https://mmif.clams.ai
Author: Brandeis Lab for Linguistics and Computation
Author-email: admin@clams.ai
Classifier: Development Status :: 5 - Production/Stable
Classifier: Intended Audience :: Developers
Classifier: Programming Language :: Python :: 3 :: Only
Requires-Python: >=3.10
License-File: LICENSE
Requires-Dist: deepdiff>5
Requires-Dist: orderly-set==5.3.*
Requires-Dist: jsonschema
Provides-Extra: seq
Requires-Dist: numpy; extra == "seq"
Provides-Extra: cv
Requires-Dist: pillow; extra == "cv"
Requires-Dist: opencv-python; extra == "cv"
Requires-Dist: ffmpeg-python; extra == "cv"
Requires-Dist: wurlitzer; extra == "cv"
Provides-Extra: dev
Requires-Dist: pytest; extra == "dev"
Requires-Dist: pytest-pep8; extra == "dev"
Requires-Dist: pytest-cov; extra == "dev"
Requires-Dist: pytype; extra == "dev"
Dynamic: author
Dynamic: author-email
Dynamic: classifier
Dynamic: description
Dynamic: description-content-type
Dynamic: home-page
Dynamic: license-file
Dynamic: provides-extra
Dynamic: requires-dist
Dynamic: requires-python
Dynamic: summary
